{
    "key": "opening",
    "type": "number",
    "label": "Opening Width (Meters)",
    "snake_case": false,
    "help": {
        "fr": {
            "text": "Largeur minimale de passage dans la chicane, en mètres arrondis au cm. S'il y a plusieurs valeurs, on renseigne uniquement la plus petite car c'est celle-là qui sera limitante.",
            "schema": {
                "url": "https://wiki.openstreetmap.org/w/images/3/38/Cycle_barrier_double_distances.png",
                "credits": "Supaplex030, CC-BY-SA 4.0"
            }
        },
        "en": {
            "text": "minimum width of the barrier",
            "picture": {
                "url": "https://wiki.openstreetmap.org/w/images/3/38/Cycle_barrier_double_distances.png",
                "credits": "Supaplex030, CC-BY-SA 4.0"
            }
        }
    },
    "prerequisiteTag": {
        "key": "cycle_barrier",
        "valueNot": "single"
    }
}
